fixmefinder/__init__.py
fixmefinder/entry.py
fixmefinder/file_updater.py
fixmefinder/finder.py
fixmefinder/issuemaker.py
fixmefinder/linear.py
fixmefinder/main.py
fixmefinder-0.1.0.dist-info/METADATA
fixmefinder-0.1.0.dist-info/WHEEL
fixmefinder-0.1.0.dist-info/entry_points.txt
fixmefinder-0.1.0.dist-info/licenses/LICENSE
fixmefinder-0.1.0.dist-info/RECORD
